MANIFEST.in
README
setup.py
debian/changelog
debian/compat
debian/control
debian/copyright
debian/rules
pglogs/__init__.py
pglogs/models.py
pglogs/monkey.py
pglogs/utils.py
pglogs.egg-info/PKG-INFO
pglogs.egg-info/SOURCES.txt
pglogs.egg-info/dependency_links.txt
pglogs.egg-info/requires.txt
pglogs.egg-info/top_level.txt