Metadata-Version: 1.0
Name: pglogs
Version: 0.1.5
Summary: A simple lib for postgres logging
Home-page: https://github.com/romario8/pglogs
Author: Roman Dashevsky
Author-email: dashevsky@selectel.ru
License: LICENSE
Platform: UNKNOWN
